llm_sql_prompt/__init__.py
llm_sql_prompt/mysql.py
llm_sql_prompt/postgres.py
llm_sql_prompt/sqlite.py
llm_sql_prompt/util.py
llm_sql_prompt-0.10.0.dist-info/METADATA
llm_sql_prompt-0.10.0.dist-info/WHEEL
llm_sql_prompt-0.10.0.dist-info/entry_points.txt
llm_sql_prompt-0.10.0.dist-info/licenses/LICENSE
llm_sql_prompt-0.10.0.dist-info/RECORD
