Metadata-Version: 2.4
Name: llm-sql-prompt
Version: 0.10.0
Summary: Utility to generate ChatGPT prompts for SQL writing, offering table structure snapshots and sample row data from Postgres and sqlite databases.
Project-URL: Homepage, https://pypi.org/project/llm-sql-prompt/
Author-email: Michael Bianco <mike@mikebian.co>
License-File: LICENSE
Keywords: chatgpt,database,llms,postgres,prompt,sql,sqlite
Requires-Python: ~=3.11
Requires-Dist: click<9,>=8.1.7
Requires-Dist: mysql-connector-python>=9.2.0
Requires-Dist: psycopg[binary]>=3.1
